vos/__init__.py
vos/commonparser.py
vos/logExceptions.py
vos/md5_cache.py
vos/node_cache.py
vos/version.py
vos/vos.py
vos/vosconfig.py
vos/commands/__init__.py
vos/commands/interrupt_exception.py
vos/commands/vcat.py
vos/commands/vchmod.py
vos/commands/vcp.py
vos/commands/vln.py
vos/commands/vlock.py
vos/commands/vls.py
vos/commands/vmkdir.py
vos/commands/vmv.py
vos/commands/vrm.py
vos/commands/vrmdir.py
vos/commands/vsync.py
vos/commands/vtag.py
vos/commands/tests/__init__.py
vos/commands/tests/test_cli.py
vos/commands/tests/test_vls.py
vos/commands/tests/test_vsync.py
vos/commands/tests/data/help_vcat.txt
vos/commands/tests/data/help_vchmod.txt
vos/commands/tests/data/help_vcp.txt
vos/commands/tests/data/help_vln.txt
vos/commands/tests/data/help_vlock.txt
vos/commands/tests/data/help_vls.txt
vos/commands/tests/data/help_vmkdir.txt
vos/commands/tests/data/help_vmv.txt
vos/commands/tests/data/help_vrm.txt
vos/commands/tests/data/help_vrmdir.txt
vos/commands/tests/data/help_vsync.txt
vos/commands/tests/data/help_vtag.txt
vos/commands/tests/data/vcat.txt
vos/commands/tests/data/vchmod.txt
vos/commands/tests/data/vcp.txt
vos/commands/tests/data/vln.txt
vos/commands/tests/data/vlock.txt
vos/commands/tests/data/vls.txt
vos/commands/tests/data/vmkdir.txt
vos/commands/tests/data/vmv.txt
vos/commands/tests/data/vrm.txt
vos/commands/tests/data/vrmdir.txt
vos/commands/tests/data/vsync.txt
vos/commands/tests/data/vtag.txt
vos/data/default-vos-config
vos/tests/__init__.py
vos/tests/test_commonparser.py
vos/tests/test_config.py
vos/tests/test_md5_cache.py
vos/tests/test_node_cache.py
vos/tests/test_vofile.py
vos/tests/test_vos.py
vos/tests/data/default-vos-config
vos-3.6.4.dist-info/licenses/LICENSE
vos-3.6.4.dist-info/METADATA
vos-3.6.4.dist-info/WHEEL
vos-3.6.4.dist-info/entry_points.txt
vos-3.6.4.dist-info/top_level.txt
vos-3.6.4.dist-info/RECORD
