Metadata-Version: 2.4
Name: vos
Version: 3.6.4
Summary: CADC VOS Class Libraries
Home-page: https://www.canfar.net/en/docs/storage
Author: JJ Kavelaars, Canadian Astronomy Data Centre
Author-email: cadc@nrc-cnrc.gc.ca
License: AGPLv3
Project-URL: Source, https://github.com/opencadc/vostools
Project-URL: Issues, https://github.com/opencadc/vostools/issues
Project-URL: VOSpace Standard, http://www.ivoa.net/documents/VOSpace/
Classifier: Natural Language :: English
Classifier: License :: OSI Approved :: GNU Affero General Public License v3
Classifier: Programming Language :: Python
Classifier: Programming Language :: Python :: 3
Requires-Python: >=3.7, <4
License-File: LICENSE
Requires-Dist: html2text>=2016.5.29
Requires-Dist: cadcutils>=1.5.4
Requires-Dist: aenum
Provides-Extra: test
Requires-Dist: pytest>=4.6; extra == "test"
Requires-Dist: pytest-cov>=2.5.1; extra == "test"
Requires-Dist: flake8>=3.4.1; extra == "test"
Dynamic: author
Dynamic: author-email
Dynamic: classifier
Dynamic: description
Dynamic: home-page
Dynamic: license
Dynamic: license-file
Dynamic: project-url
Dynamic: requires-dist
Dynamic: requires-python
Dynamic: summary
